gptq_Quantizer/__init__.py
gptq_Quantizer/gptq_Quantizer.py
gptq_Quantizer/utils.py
gptq_Quantizer-1.0.dist-info/METADATA
gptq_Quantizer-1.0.dist-info/WHEEL
gptq_Quantizer-1.0.dist-info/top_level.txt
gptq_Quantizer-1.0.dist-info/RECORD
