Metadata-Version: 2.1
Name: gptq-Quantizer
Version: 1.0
Summary: A Python package for GPTQ quantization
Author: Kirouane Ayoub
Author-email: ayoubkirouane3@email.com
Requires-Dist: transformers
Requires-Dist: torch
Requires-Dist: optimum ==1.13.2
Requires-Dist: auto-gptq ==0.4.2
